component_distribution_px01.py
component_distribution_px01-0.1.0.dist-info/METADATA
component_distribution_px01-0.1.0.dist-info/WHEEL
component_distribution_px01-0.1.0.dist-info/entry_points.txt
component_distribution_px01-0.1.0.dist-info/RECORD
