Metadata-Version: 2.4
Name: component-distribution-px01
Version: 0.1.0
Summary: Add your description here
Requires-Python: <4,>=3.13
Requires-Dist: pydantic~=2.7
